lavajung/__init__.py
lavajung/emoji-data.txt
lavajung/parser.py
lavajung/unipy.pyc
lavajung/utils.py
lavajung-1.3.dist-info/METADATA
lavajung-1.3.dist-info/WHEEL
lavajung-1.3.dist-info/top_level.txt
lavajung-1.3.dist-info/RECORD
