Metadata-Version: 2.4
Name: lavajung
Version: 1.3
Summary: a basic emoji package
Author: kubet
Author-email: kubet@atomicmail.io
License: Apache License 2.0
Dynamic: author
Dynamic: author-email
Dynamic: description
Dynamic: description-content-type
Dynamic: license
Dynamic: summary
